buildozer/__init__.py
buildozer/__main__.py
buildozer/default.spec
buildozer/jsonstore.py
buildozer/sitecustomize.py
buildozer/target.py
buildozer/libs/__init__.py
buildozer/libs/_structures.py
buildozer/libs/version.py
buildozer/scripts/__init__.py
buildozer/scripts/client.py
buildozer/scripts/remote.py
buildozer/targets/__init__.py
buildozer/targets/android.py
buildozer/targets/ios.py
buildozer/targets/osx.py
buildozer-1.5.0.dist-info/LICENSE
buildozer-1.5.0.dist-info/METADATA
buildozer-1.5.0.dist-info/WHEEL
buildozer-1.5.0.dist-info/entry_points.txt
buildozer-1.5.0.dist-info/top_level.txt
buildozer-1.5.0.dist-info/RECORD
