Metadata-Version: 2.1
Name: buildozer
Version: 1.5.0
Summary: Generic Python packager for Android / iOS and Desktop
Home-page: https://github.com/kivy/buildozer
Author: Mathieu Virbel
Author-email: mat@kivy.org
License: MIT
Classifier: Development Status :: 5 - Production/Stable
Classifier: Intended Audience :: Developers
Classifier: Topic :: Software Development :: Build Tools
Classifier: Programming Language :: Python :: 3
Classifier: Programming Language :: Python :: 3.6
Classifier: Programming Language :: Python :: 3.7
Classifier: Programming Language :: Python :: 3.8
License-File: LICENSE
